{
  "Постановка целей проекта": [
    {
      "skill": "Постановка целей проекта",
      "title": "Старт нового проекта",
      "steps": [
        {
          "id": 1,
          "type": "choice",
          "text": "Команда начинает новый проект, но формулировка цели пока слишком размытая. Какой первый шаг вы выберете?",
          "options": [
            {
              "text": "Сразу раздать задачи без уточнения ожидаемого результата.",
              "score": 2,
              "feedback": "Команда начинает работу быстро, но риск неверного направления высокий."
            },
            {
              "text": "Собрать короткую сессию и уточнить цель по SMART-критериям.",
              "score": 4,
              "feedback": "Отличный выбор: это создает понятный ориентир для всей команды."
            },
            {
              "text": "Оставить формулировку цели как есть и вернуться к ней в конце этапа.",
              "score": 0,
              "feedback": "Позднее уточнение цели обычно приводит к переработкам."
            }
          ]
        },
        {
          "id": 2,
          "type": "choice",
          "text": "После уточнения цели часть участников просит зафиксировать критерии успеха. Как вы поступите?",
          "options": [
            {
              "text": "Определю измеримые метрики и согласую их с заказчиком.",
              "score": 4,
              "feedback": "Сильное решение: измеримые критерии повышают управляемость проекта."
            },
            {
              "text": "Ограничусь общей формулировкой «сделать качественно».",
              "score": 2,
              "feedback": "Слишком общая формулировка усложнит оценку прогресса."
            },
            {
              "text": "Не буду фиксировать критерии, чтобы сохранить гибкость.",
              "score": 0,
              "feedback": "Гибкость полезна, но без критериев команда теряет фокус."
            }
          ]
        },
        {
          "id": 3,
          "type": "choice",
          "text": "Через некоторое время команда замечает, что цели понятны не всем одинаково. Что сделаете, чтобы устранить расхождения?",
          "options": [
            {
              "text": "Проведу короткую повторную синхронизацию и уточню формулировки для всех участников.",
              "score": 4,
              "feedback": "Хорошее решение: повторная синхронизация снижает риск разночтений."
            },
            {
              "text": "Поручу каждому интерпретировать цель самостоятельно.",
              "score": 2,
              "feedback": "Самостоятельные интерпретации часто приводят к расхождению ожиданий."
            },
            {
              "text": "Решу, что уточнения уже не нужны, и перейду к исполнению.",
              "score": 2,
              "feedback": "Переход к работе без единого понимания может привести к переработкам."
            }
          ]
        },
        {
          "id": 4,
          "type": "choice",
          "text": "Проект готов к запуску, у команды есть черновая дорожная карта. Что сделаете перед стартом выполнения?",
          "options": [
            {
              "text": "Проведу финальную синхронизацию целей, метрик и ролей.",
              "score": 4,
              "feedback": "Отличный финальный шаг: снижает риск разночтений на старте."
            },
            {
              "text": "Начну сразу выполнение, чтобы не тратить время на обсуждения.",
              "score": 2,
              "feedback": "Можно ускориться, но цена ошибки на старте часто выше."
            },
            {
              "text": "Передам запуск одному участнику без общей синхронизации.",
              "score": -2,
              "feedback": "Без общей синхронизации часть команды может неверно понять цель."
            }
          ]
        }
      ]
    }
  ],
  "Принятие управленческих решений": [
    {
      "skill": "Принятие управленческих решений",
      "title": "Выбор при ограниченных ресурсах",
      "steps": [
        {
          "id": 1,
          "type": "choice",
          "text": "Команда ограничена бюджетом и временем: нужно выбрать приоритет на ближайший спринт. Как вы примете первое решение?",
          "options": [
            {
              "text": "Сопоставлю варианты по рискам, срокам и влиянию на пользователей.",
              "score": 4,
              "feedback": "Верный управленческий подход: решение становится обоснованным."
            },
            {
              "text": "Выберу вариант, который кажется самым простым лично мне.",
              "score": 2,
              "feedback": "Личная интуиция полезна, но без критериев риск ошибки выше."
            },
            {
              "text": "Отложу решение и продолжу текущие задачи без изменений.",
              "score": 0,
              "feedback": "Отсрочка решения может увеличить организационные потери."
            }
          ]
        },
        {
          "id": 2,
          "type": "choice",
          "text": "После предварительного анализа мнения стейкхолдеров разделились. Как будете согласовывать итог?",
          "options": [
            {
              "text": "Покажу критерии, сценарии последствий и предложу компромиссный план.",
              "score": 4,
              "feedback": "Отлично: прозрачная аргументация облегчает согласование."
            },
            {
              "text": "Приму решение единолично без обсуждения.",
              "score": 2,
              "feedback": "Иногда быстро, но часто снижает вовлеченность и поддержку."
            },
            {
              "text": "Попрошу команду голосовать без контекста.",
              "score": 2,
              "feedback": "Без контекста голосование не гарантирует качественное решение."
            }
          ]
        },
        {
          "id": 3,
          "type": "choice",
          "text": "После согласования появляется новая информация, которая меняет часть предпосылок. Как вы скорректируете решение?",
          "options": [
            {
              "text": "Пересмотрю решение по тем же критериям и сообщу, что изменилось.",
              "score": 4,
              "feedback": "Сильный управленческий подход: решение адаптируется к новым данным, но не теряет прозрачности."
            },
            {
              "text": "Оставлю всё как есть, чтобы не путать команду.",
              "score": 2,
              "feedback": "Стабильность важна, но игнорирование новых данных может привести к ошибке."
            },
            {
              "text": "Полностью отменю прежнее решение без объяснений.",
              "score": -2,
              "feedback": "Изменение возможно, но без объяснения команда теряет ориентиры."
            }
          ]
        },
        {
          "id": 4,
          "type": "choice",
          "text": "Решение принято, необходимо подготовить план реализации. Как вы оформите следующее действие?",
          "options": [
            {
              "text": "Зафиксирую решение, владельцев задач и контрольные точки проверки.",
              "score": 4,
              "feedback": "Сильная управленческая практика: решение переходит в управляемое исполнение."
            },
            {
              "text": "Ограничусь устным сообщением команде.",
              "score": 2,
              "feedback": "Без фиксации возрастает риск недопонимания."
            },
            {
              "text": "Передам реализацию одному человеку без распределения ролей.",
              "score": 0,
              "feedback": "Это создаст узкое место и повышенный риск срыва."
            }
          ]
        }
      ]
    }
  ],
  "Коммуникации в команде": [
    {
      "skill": "Коммуникации в команде",
      "title": "Задержка части работы",
      "steps": [
        {
          "id": 1,
          "type": "choice",
          "text": "Перед демонстрацией один участник сообщает о задержке ключевого блока. Какой будет ваша первая реакция?",
          "options": [
            {
              "text": "Созвать быструю синхронизацию и уточнить критические зависимости.",
              "score": 4,
              "feedback": "Отлично: вы снижаете неопределенность и удерживаете фокус."
            },
            {
              "text": "Подождать, пока участник сам решит проблему.",
              "score": 2,
              "feedback": "Пассивный подход повышает риск срыва дедлайна."
            },
            {
              "text": "Публично обвинить участника в задержке.",
              "score": -2,
              "feedback": "Конфликтный тон ухудшает командную динамику."
            }
          ]
        },
        {
          "id": 2,
          "type": "choice",
          "text": "Команда готова перераспределить задачи, но нужно быстро договориться о формате взаимодействия. Как организуете коммуникацию?",
          "options": [
            {
              "text": "Определю канал, короткие статусы и ответственных за обновления.",
              "score": 4,
              "feedback": "Структура коммуникации помогает избежать хаоса."
            },
            {
              "text": "Оставлю общение в свободном формате без правил.",
              "score": 2,
              "feedback": "Свобода полезна, но в кризисе нужна четкость."
            },
            {
              "text": "Передам все сообщения через одного человека без резервов.",
              "score": 2,
              "feedback": "Это создает узкое место и риск потери информации."
            }
          ]
        },
        {
          "id": 3,
          "type": "choice",
          "text": "Во время работы часть команды начинает по-разному понимать приоритеты. Что сделаете, чтобы вернуть единое понимание?",
          "options": [
            {
              "text": "Сформулирую общий приоритет, коротко повторю план и уточню зоны ответственности.",
              "score": 4,
              "feedback": "Сильное коммуникационное действие: команда снова получает единый ориентир."
            },
            {
              "text": "Предложу каждому самому решить, что сейчас важнее.",
              "score": 2,
              "feedback": "Без общей рамки команда может распылить усилия."
            },
            {
              "text": "Ограничусь общим сообщением без уточнений.",
              "score": 2,
              "feedback": "Общее сообщение полезно, но без конкретики не всегда устраняет путаницу."
            }
          ]
        },
        {
          "id": 4,
          "type": "choice",
          "text": "До демонстрации осталось мало времени, команда ждет финального решения. Что вы сообщите команде в конце?",
          "options": [
            {
              "text": "Кратко подведу итог, подтвержу план и критерии готовности.",
              "score": 4,
              "feedback": "Сильное завершение: у команды единое понимание приоритета."
            },
            {
              "text": "Ограничусь сообщением «делаем как получится».",
              "score": 2,
              "feedback": "Неопределенный сигнал снижает качество исполнения."
            },
            {
              "text": "Перенесу ответственность целиком на команду без координации.",
              "score": 0,
              "feedback": "Лидерская координация особенно важна в условиях дедлайна."
            }
          ]
        }
      ]
    }
  ],
  "Планирование этапов проекта": [
    {
      "skill": "Планирование этапов проекта",
      "title": "Плотный календарь этапов",
      "steps": [
        {
          "id": 1,
          "type": "choice",
          "text": "Этапы проекта определены, но взаимосвязи и точки контроля пока не описаны. С чего начнете планирование?",
          "options": [
            {
              "text": "Опишу зависимости между этапами и критический путь.",
              "score": 4,
              "feedback": "Отлично: это основа управляемого графика."
            },
            {
              "text": "Оставлю этапы независимыми и уточню связи позже.",
              "score": 2,
              "feedback": "Без связей сложно прогнозировать влияние задержек."
            },
            {
              "text": "Сфокусируюсь только на финальной дате сдачи.",
              "score": 2,
              "feedback": "Одна дата без промежуточных ориентиров обычно недостаточна."
            }
          ]
        },
        {
          "id": 2,
          "type": "choice",
          "text": "После первичной декомпозиции команда просит определить контрольные точки. Как поступите?",
          "options": [
            {
              "text": "Добавлю вехи с критериями готовности каждого этапа.",
              "score": 4,
              "feedback": "Хорошее решение: вехи делают прогресс прозрачным."
            },
            {
              "text": "Оставлю только еженедельные общие отчеты без критериев.",
              "score": 2,
              "feedback": "Отчеты полезны, но без критериев сложнее оценивать статус."
            },
            {
              "text": "Не буду вводить дополнительные точки контроля.",
              "score": 0,
              "feedback": "Без контроля возрастает риск позднего обнаружения проблем."
            }
          ]
        },
        {
          "id": 3,
          "type": "choice",
          "text": "В середине планирования становится ясно, что часть задач недооценена по трудозатратам. Как скорректируете план?",
          "options": [
            {
              "text": "Пересчитаю трудоемкость, обновлю зависимости и согласую изменения с командой.",
              "score": 4,
              "feedback": "Сильный подход: план уточняется на основе реальной оценки, а не предположений."
            },
            {
              "text": "Оставлю старые оценки, чтобы не терять время на пересчет.",
              "score": 2,
              "feedback": "Игнорирование новых данных может привести к срыву сроков."
            },
            {
              "text": "Сдвину дедлайн всех этапов без объяснения причин.",
              "score": 2,
              "feedback": "Сдвиг возможен, но его нужно обосновывать и увязывать с общей логикой плана."
            }
          ]
        },
        {
          "id": 4,
          "type": "choice",
          "text": "Риски задержек частично оценены, осталось решить вопрос временного буфера. Как учтете неопределенность сроков?",
          "options": [
            {
              "text": "Заложу реалистичный буфер на ключевых этапах и согласую его.",
              "score": 4,
              "feedback": "Отлично: буфер повышает устойчивость плана."
            },
            {
              "text": "Не буду использовать буфер, чтобы план выглядел жестче.",
              "score": 2,
              "feedback": "Слишком жесткий план часто срывается при первом отклонении."
            },
            {
              "text": "Увеличу все сроки без анализа причин риска.",
              "score": 0,
              "feedback": "Запас полезен, но должен быть обоснован."
            }
          ]
        }
      ]
    }
  ],
  "Анализ последствий решений": [
    {
      "skill": "Анализ последствий решений",
      "title": "Изменение функциональности",
      "steps": [
        {
          "id": 1,
          "type": "choice",
          "text": "Команда предлагает убрать часть функциональности ради ускорения релиза. Как оцените предложение?",
          "options": [
            {
              "text": "Проверю влияние на пользователей, бюджет, сроки и качество.",
              "score": 4,
              "feedback": "Отличный аналитический подход: учитываются ключевые последствия."
            },
            {
              "text": "Сразу соглашусь ради экономии времени.",
              "score": 2,
              "feedback": "Быстро, но риск скрытых потерь остается высоким."
            },
            {
              "text": "Отклоню предложение без анализа данных.",
              "score": 2,
              "feedback": "Интуитивный отказ тоже может быть ошибочным."
            }
          ]
        },
        {
          "id": 2,
          "type": "choice",
          "text": "Анализ показал неоднозначный эффект: выигрываем во времени, но теряем часть ценности. Как представите выводы стейкхолдерам?",
          "options": [
            {
              "text": "Подготовлю сценарии с плюсами, минусами и возможными компенсациями.",
              "score": 4,
              "feedback": "Прозрачная подача помогает принять зрелое решение."
            },
            {
              "text": "Сообщу только о положительных сторонах изменения.",
              "score": 2,
              "feedback": "Односторонняя информация снижает доверие."
            },
            {
              "text": "Передам итог без аргументации и сравнений.",
              "score": 0,
              "feedback": "Без аргументов сложно получить поддержку решения."
            }
          ]
        },
        {
          "id": 3,
          "type": "choice",
          "text": "После обсуждения стейкхолдеры предлагают промежуточный компромисс. Как оцените его перед внедрением?",
          "options": [
            {
              "text": "Проверю, какие потери и выгоды он дает по тем же критериям, что и основные варианты.",
              "score": 4,
              "feedback": "Отлично: компромисс тоже нужно оценивать системно, а не интуитивно."
            },
            {
              "text": "Сразу соглашусь, потому что это компромиссный вариант.",
              "score": 2,
              "feedback": "Компромисс не всегда оптимален, если его не проверить по критериям."
            },
            {
              "text": "Откажусь от него только потому, что он отличается от первоначального плана.",
              "score": 2,
              "feedback": "Сохранение исходного плана не должно быть самоцелью без анализа последствий."
            }
          ]
        },
        {
          "id": 4,
          "type": "choice",
          "text": "Команда выбрала компромиссный вариант и готова к внедрению. Что важно сделать после принятия решения?",
          "options": [
            {
              "text": "Запланировать мониторинг последствий и критерии пересмотра.",
              "score": 4,
              "feedback": "Сильное решение: вы контролируете эффект и готовы корректировать курс."
            },
            {
              "text": "Закрыть вопрос и не возвращаться к оценке результата.",
              "score": 2,
              "feedback": "Без пост-анализа можно пропустить негативные эффекты."
            },
            {
              "text": "Передать контроль только одной стороне без общих метрик.",
              "score": -2,
              "feedback": "Нужны общие метрики для объективной оценки последствий."
            }
          ]
        }
      ]
    }
  ],
  "Распределение ролей и задач": [
    {
      "skill": "Распределение ролей и задач",
      "title": "Нечеткие зоны ответственности",
      "steps": [
        {
          "id": 1,
          "type": "choice",
          "text": "В проекте появились дублирующие задачи, а часть работ осталась без владельца. Как вы начнете распределение?",
          "options": [
            {
              "text": "Определю роли по компетенциям и зафиксирую ответственность.",
              "score": 4,
              "feedback": "Отличный подход: роль и ответственность становятся прозрачными."
            },
            {
              "text": "Назначу задачи случайно, чтобы ускорить процесс.",
              "score": 2,
              "feedback": "Случайность ускоряет старт, но снижает итоговое качество."
            },
            {
              "text": "Поручу критические задачи одному сильному участнику.",
              "score": 2,
              "feedback": "Перегрузка одного человека повышает риск ошибок и выгорания."
            }
          ]
        },
        {
          "id": 2,
          "type": "choice",
          "text": "После первичного распределения команда просит уточнить зоны пересечения задач. Как устраните пересечения?",
          "options": [
            {
              "text": "Опишу интерфейсы взаимодействия и точки передачи результата.",
              "score": 4,
              "feedback": "Хорошее решение: пересечения становятся управляемыми."
            },
            {
              "text": "Оставлю команде разбираться по ситуации.",
              "score": 2,
              "feedback": "Гибкость есть, но растет риск конфликтов и потерь времени."
            },
            {
              "text": "Отменю командное взаимодействие и изолирую задачи полностью.",
              "score": 2,
              "feedback": "Полная изоляция обычно мешает целостности результата."
            }
          ]
        },
        {
          "id": 3,
          "type": "choice",
          "text": "Во время планирования выясняется, что один участник перегружен, а другой недозагружен. Как скорректируете распределение?",
          "options": [
            {
              "text": "Перераспределю задачи с учетом компетенций и текущей нагрузки.",
              "score": 4,
              "feedback": "Сильное решение: выравнивание нагрузки повышает устойчивость работы команды."
            },
            {
              "text": "Оставлю всё как есть, чтобы не тратить время на пересмотр.",
              "score": 2,
              "feedback": "Игнорирование дисбаланса часто приводит к узким местам."
            },
            {
              "text": "Передам все дополнительные задачи самому сильному участнику.",
              "score": 2,
              "feedback": "Это может ускорить часть работ, но создаст высокий риск перегрузки."
            }
          ]
        },
        {
          "id": 4,
          "type": "choice",
          "text": "Перед стартом выполнения осталось проверить равномерность загрузки команды. Ваше финальное действие?",
          "options": [
            {
              "text": "Проверю баланс нагрузки и при необходимости скорректирую назначения.",
              "score": 4,
              "feedback": "Отлично: сбалансированная загрузка повышает стабильность исполнения."
            },
            {
              "text": "Оставлю текущую нагрузку без проверки.",
              "score": 2,
              "feedback": "Без проверки легко пропустить узкие места."
            },
            {
              "text": "Сокращу количество участников для упрощения контроля.",
              "score": 2,
              "feedback": "Иногда полезно, но может усилить перегрузку оставшихся."
            }
          ]
        }
      ]
    }
  ],
  "Управление рисками проекта": [
    {
      "skill": "Управление рисками проекта",
      "title": "Появление внешнего риска",
      "steps": [
        {
          "id": 1,
          "type": "choice",
          "text": "Поставщик предупреждает о вероятной задержке критически важных материалов. Какой шаг выполните первым?",
          "options": [
            {
              "text": "Зарегистрирую риск и оценю вероятность и влияние.",
              "score": 4,
              "feedback": "Сильный старт: риск становится управляемым."
            },
            {
              "text": "Подожду фактической задержки и затем решу по ситуации.",
              "score": 2,
              "feedback": "Реактивный подход увеличивает потенциальный ущерб."
            },
            {
              "text": "Сразу отменю текущий план без анализа.",
              "score": 0,
              "feedback": "Радикальные решения без анализа часто неоптимальны."
            }
          ]
        },
        {
          "id": 2,
          "type": "choice",
          "text": "Оценка показала среднюю вероятность и высокое влияние задержки на сроки. Какой план реагирования выберете?",
          "options": [
            {
              "text": "Подготовлю резервный сценарий с альтернативным поставщиком.",
              "score": 4,
              "feedback": "Отличное решение: вы снижаете зависимость от одного источника."
            },
            {
              "text": "Ограничусь наблюдением без подготовленного плана.",
              "score": 2,
              "feedback": "Мониторинг полезен, но без плана реакция будет запоздалой."
            },
            {
              "text": "Переложу риск на команду без распределения ответственности.",
              "score": 2,
              "feedback": "Нужны конкретные владельцы и действия."
            }
          ]
        },
        {
          "id": 3,
          "type": "choice",
          "text": "Появились признаки, что риск может реализоваться раньше ожидаемого. Что сделаете на этом этапе?",
          "options": [
            {
              "text": "Пересмотрю оценку риска, уточню статус и заранее активирую часть мер реагирования.",
              "score": 4,
              "feedback": "Отлично: вы не ждете критической точки и действуете проактивно."
            },
            {
              "text": "Продолжу наблюдать без изменений, пока проблема не станет очевидной.",
              "score": 2,
              "feedback": "Ожидание может сократить время на реакцию и усилить ущерб."
            },
            {
              "text": "Сразу переведу весь проект в аварийный режим без дополнительной проверки.",
              "score": 2,
              "feedback": "Реагировать важно, но слишком резкие меры без уточнения могут быть избыточными."
            }
          ]
        },
        {
          "id": 4,
          "type": "choice",
          "text": "Команда согласовала меры, осталось встроить контроль в регулярный ритм проекта. Как закрепите управление риском?",
          "options": [
            {
              "text": "Назначу владельца риска и график периодического пересмотра.",
              "score": 4,
              "feedback": "Хорошая практика: риск контролируется системно."
            },
            {
              "text": "Не буду фиксировать владельца, чтобы все отвечали вместе.",
              "score": 2,
              "feedback": "Без владельца риск часто остается без фактического контроля."
            },
            {
              "text": "Вернусь к риску только если появится критическая проблема.",
              "score": -2,
              "feedback": "Поздняя реакция обычно обходится дороже."
            }
          ]
        }
      ]
    }
  ]
}
